chat_input_advanced/__init__.py
chat_input_advanced/frontend/build/asset-manifest.json
chat_input_advanced/frontend/build/bootstrap.min.css
chat_input_advanced/frontend/build/bootstrap.min.css.map
chat_input_advanced/frontend/build/index.html
chat_input_advanced/frontend/build/static/css/main.028a5858.css
chat_input_advanced/frontend/build/static/css/main.028a5858.css.map
chat_input_advanced/frontend/build/static/js/main.83554b9b.js
chat_input_advanced/frontend/build/static/js/main.83554b9b.js.LICENSE.txt
chat_input_advanced/frontend/build/static/js/main.83554b9b.js.map
streamlit_chat_input_advanced-0.0.17.dist-info/LICENSE
streamlit_chat_input_advanced-0.0.17.dist-info/METADATA
streamlit_chat_input_advanced-0.0.17.dist-info/WHEEL
streamlit_chat_input_advanced-0.0.17.dist-info/top_level.txt
streamlit_chat_input_advanced-0.0.17.dist-info/RECORD
